chopro/__init__.py
chopro/chopro2html.py
chopro/core.py
chopro/utils.py
chopro-0.2.0.dist-info/DESCRIPTION.rst
chopro-0.2.0.dist-info/METADATA
chopro-0.2.0.dist-info/RECORD
chopro-0.2.0.dist-info/WHEEL
chopro-0.2.0.dist-info/entry_points.txt
chopro-0.2.0.dist-info/metadata.json
chopro-0.2.0.dist-info/top_level.txt
