Metadata-Version: 2.0
Name: chopro
Version: 0.2.0
Summary: Utilities for manipulating, converting, and rendering ChoPro/ChordPro text
Home-page: https://github.com/jontsai/pychopro
Author: Jonathan Tsai
Author-email: hello@jontsai.com
License: MIT
Keywords: chopro chordpro music lyrics chords
Platform: UNKNOWN
Classifier: Development Status :: 3 - Alpha
Classifier: Intended Audience :: Developers
Classifier: Topic :: Text Processing :: General
Classifier: License :: OSI Approved :: MIT License
Classifier: Programming Language :: Python :: 2
Classifier: Programming Language :: Python :: 2.7
Classifier: Programming Language :: Python :: 3
Provides-Extra: dev
Provides-Extra: test
